censys_maltego/__init__.py
censys_maltego/resources/__init__.py
censys_maltego/resources/etc/__init__.py
censys_maltego/resources/etc/censys_maltego.conf
censys_maltego/resources/external/__init__.py
censys_maltego/resources/images/__init__.py
censys_maltego/resources/maltego/__init__.py
censys_maltego/transforms/__init__.py
censys_maltego/transforms/certificatecontext.py
censys_maltego/transforms/certificatetoipaddresses.py
censys_maltego/transforms/domaintoipaddress.py
censys_maltego/transforms/domaintosubdomains.py
censys_maltego/transforms/ipaddresstoasn.py
censys_maltego/transforms/ipaddresstocertificate.py
censys_maltego/transforms/ipaddresstodomains.py
censys_maltego/transforms/ipaddresstolocation.py
censys_maltego/transforms/ipaddresstoports.py
censys_maltego/transforms/ipaddresstoservices.py
censys_maltego/transforms/common/__init__.py
censys_maltego/transforms/common/entities.py
censys_maltego/transforms/common/utils.py
censys_maltego-2.0.0.dist-info/LICENSE
censys_maltego-2.0.0.dist-info/METADATA
censys_maltego-2.0.0.dist-info/WHEEL
censys_maltego-2.0.0.dist-info/top_level.txt
censys_maltego-2.0.0.dist-info/RECORD
