Metadata-Version: 2.1
Name: censys-maltego
Version: 2.0.0
Summary: This package provides an interface into Censys from Maltego.
Home-page: UNKNOWN
Author: Censys Team
Author-email: support@censys.io
License: Apache License, Version 2.0
Project-URL: Censys Homepage, https://censys.io/
Project-URL: Changelog, https://github.com/censys/censys-maltego/releases
Project-URL: Tracker, https://github.com/censys/censys-maltego/issues
Project-URL: Source, https://github.com/censys/censys-maltego
Keywords: censys,search,maltego
Platform: UNKNOWN
Classifier: Topic :: Internet
Classifier: Topic :: Security
Classifier: Topic :: Internet :: WWW/HTTP :: Indexing/Search
Classifier: Topic :: Software Development :: Libraries :: Python Modules
Classifier: Framework :: Flake8
Classifier: Natural Language :: English
Classifier: Intended Audience :: Developers
Classifier: Operating System :: OS Independent
Classifier: Development Status :: 5 - Production/Stable
Classifier: License :: OSI Approved :: Apache Software License
Classifier: Programming Language :: Python
Classifier: Programming Language :: Python :: 3
Classifier: Programming Language :: Python :: 3.6
Classifier: Programming Language :: Python :: 3.7
Classifier: Programming Language :: Python :: 3.8
Classifier: Programming Language :: Python :: 3.9
Classifier: Programming Language :: Python :: Implementation :: PyPy
Requires-Python: >=3.6.0
Requires-Dist: canari (<4,>=3.3.10)
Requires-Dist: censys (==2.0.0)
Provides-Extra: dev
Requires-Dist: flake8 (==3.9.1) ; extra == 'dev'
Requires-Dist: flake8-docstrings (==1.6.0) ; extra == 'dev'
Requires-Dist: flake8-pytest-style (==1.4.1) ; extra == 'dev'
Requires-Dist: flake8-simplify (==0.14.0) ; extra == 'dev'
Requires-Dist: flake8-comprehensions (==3.4.0) ; extra == 'dev'
Requires-Dist: pep8-naming (==0.11.1) ; extra == 'dev'
Requires-Dist: flake8-black (==0.2.1) ; extra == 'dev'
Requires-Dist: black (==20.8b1) ; extra == 'dev'
Requires-Dist: pytest (==6.2.3) ; extra == 'dev'
Requires-Dist: pytest-cov (==2.11.1) ; extra == 'dev'
Requires-Dist: responses (==0.13.2) ; extra == 'dev'
Requires-Dist: mypy (==0.812) ; extra == 'dev'
Requires-Dist: twine (==3.4.1) ; extra == 'dev'
Requires-Dist: parameterized (==0.8.1) ; extra == 'dev'
